metsuri/VERSION
metsuri/__init__.py
metsuri/log_check.py
metsuri/log_download.py
metsuri/log_generate.py
metsuri/log_uploader.py
metsuri/serial_logger.py
metsuri-0.5.0.dist-info/LICENSE
metsuri-0.5.0.dist-info/METADATA
metsuri-0.5.0.dist-info/WHEEL
metsuri-0.5.0.dist-info/entry_points.txt
metsuri-0.5.0.dist-info/top_level.txt
metsuri-0.5.0.dist-info/RECORD
