Metadata-Version: 2.1
Name: metsuri
Version: 0.5.0
Summary: Serial log collector and uploader
Home-page: https://github.com/koneopen/metsuri
Author: Sami J. Lehtinen
Author-email: sami.lehtinen@kone.com
Classifier: Programming Language :: Python :: 3
Classifier: License :: OSI Approved :: MIT License
Classifier: Operating System :: OS Independent
Requires-Python: >=3.7
License-File: LICENSE
Requires-Dist: docopt (>=0.6.2)
Requires-Dist: boto3 (>=1.16)
Requires-Dist: pyserial (>=3.4)
Requires-Dist: rich (>=9.0)
Provides-Extra: dev
Requires-Dist: freezegun ; extra == 'dev'
Requires-Dist: pytest ; extra == 'dev'
Requires-Dist: tox ; extra == 'dev'
Requires-Dist: tox-pyenv ; extra == 'dev'
Requires-Dist: wheel ; extra == 'dev'
